{"contacts":"[{\"prename\":\"Thomas\",\"name\":\"Fischer\",\"short_name\":\"TF\",\"email\":\"fischer@gmail.com\",\"password\":\"test123\",\"phone\":\"\",\"favouriteColor\":\"hsl(135, 100%, 50%)\"},{\"prename\":\"Martin\",\"name\":\"Kurzer\",\"short_name\":\"MK\",\"email\":\"kurzer@dev.com\",\"password\":\"test123\",\"phone\":\"+49172911231\",\"favouriteColor\":\"rgba(255, 122, 0, 1)\"},{\"prename\":\"Lutz\",\"name\":\"Martin\",\"short_name\":\"LM\",\"email\":\"martin@dev.com\",\"password\":\"test123\",\"phone\":\"+49172911231\",\"favouriteColor\":\"rgba(255, 122, 0, 1)\"},{\"prename\":\"Hans\",\"name\":\"Mayring\",\"short_name\":\"HM\",\"email\":\"mayring@gmail.com\",\"password\":\"test123\",\"phone\":\"+49156123112\",\"favouriteColor\":\"rgba(255, 122, 0, 1)\"},{\"prename\":\"Johannes\",\"name\":\"Meier\",\"short_name\":\"JM\",\"email\":\"meier@gmail.com\",\"password\":\"Test123\",\"phone\":\"4565456456456\",\"favouriteColor\":\"hsl(71, 100%, 50%)\"},{\"prename\":\"Hans\",\"name\":\"Peter\",\"short_name\":\"HP\",\"email\":\"peter@gmail.com\",\"password\":\"test123\",\"phone\":\"49172918123\",\"favouriteColor\":\"rgba(255, 122, 0, 1)\"},{\"prename\":\"Max\",\"name\":\"Scheel\",\"short_name\":\"MS\",\"email\":\"scheel@gmail.com\",\"password\":\"Test123\",\"phone\":\"43455353543\",\"favouriteColor\":\"hsl(324, 100%, 50%)\"},{\"prename\":\"Thomas\",\"name\":\"Schmidt\",\"short_name\":\"TS\",\"email\":\"schmidt@gmail.com\",\"password\":\"test123\",\"phone\":\"49172918123\",\"favouriteColor\":\"rgba(255, 122, 0, 1)\"},{\"prename\":\"Peter\",\"name\":\"Schwarz\",\"short_name\":\"PS\",\"email\":\"schwarz@gmail.com\",\"password\":\"test123\",\"phone\":\"+491729189980\",\"favouriteColor\":\"rgba(255, 122, 0, 1)\"},{\"prename\":\"Johannes\",\"name\":\"Thorghast\",\"short_name\":\"JT\",\"email\":\"th@dev.com\",\"password\":\"test123\",\"phone\":\"+491756931123\",\"favouriteColor\":\"rgba(255, 122, 0, 1)\"}]","currentUser":"{\"prename\":\"Guest\",\"name\":\"\",\"short_name\":\"G\",\"email\":\"\",\"password\":\"\",\"phone\":\"\",\"favouriteColor\":\"HSL(150, 100%, 50%)\"}","allTasks":"[{\"title\":\"Baum fällen\",\"description\":\"Osterwald bitte nutzen!\",\"category\":[\"Organisieren\",\"blue\"],\"color\":\"blue\",\"date\":\"2023-05-13\",\"contactNames\":[\"Hans Mayring\"],\"priority\":\"Urgent\",\"subtasks\":[{\"name\":\"df\",\"state\":\"todo\"}],\"id\":0,\"state\":\"todo\",\"subtasksChecked\":[]},{\"title\":\"Oswald grüßen\",\"description\":\"dsdfd\",\"category\":[\"Organisieren\",\"blue\"],\"color\":[],\"date\":\"2023-05-13\",\"contactNames\":[\"Hans Mayring\"],\"priority\":\"Low\",\"subtasks\":[{\"name\":\"fs\",\"state\":\"isChecked\"}],\"id\":1,\"state\":\"done\",\"subtasksChecked\":[\"fs\"]},{\"title\":\"Oswald ablehnend ansehen\",\"description\":\"fdsdsf\",\"category\":[\"Oswald\",\"red\"],\"color\":\"red\",\"date\":\"2023-05-13\",\"contactNames\":[\"Johannes Thorghast\"],\"priority\":\"Low\",\"subtasks\":[{\"name\":\"dsds\",\"state\":\"isChecked\"}],\"id\":2,\"state\":\"done\",\"subtasksChecked\":[\"dsds\"]},{\"title\":\"Capture the Flag\",\"description\":\"Red flag, blue flag\",\"category\":[\"Games\",\"turquoise\"],\"color\":\"turquoise\",\"date\":\"2023-05-21\",\"contactNames\":[\"Lutz Martin\",\"Martin Kurzer\",\"Johannes Meier\",\"Hans Peter\",\"Johannes Thorghast\"],\"priority\":\"Medium\",\"subtasks\":[{\"name\":\"Alle Einladungen verschicken\",\"state\":\"todo\"}],\"id\":3,\"state\":\"progress\",\"subtasksChecked\":[]}]","counts":"[{\"todoCount\":1,\"progressCount\":1,\"feedbackCount\":0,\"doneCount\":2,\"boardCount\":4}]","prioCount":"1","categories":"[[\"Games\",\"turquoise\"],[\"Organisieren\",\"blue\"],[\"Oswald\",\"red\"]]"}